README.md
setup.py
PqrUpload4_pkg_petronije.egg-info/PKG-INFO
PqrUpload4_pkg_petronije.egg-info/SOURCES.txt
PqrUpload4_pkg_petronije.egg-info/dependency_links.txt
PqrUpload4_pkg_petronije.egg-info/top_level.txt
PqrUploadModule/__init__.py
PqrUploadModule/_scan.py
PqrUploadModule/actions.py
PqrUploadModule/actions_notes_counterparts.py
PqrUploadModule/api_functions.py
PqrUploadModule/attachment_counterparts.py
PqrUploadModule/attachments.py
PqrUploadModule/authorizations.py
PqrUploadModule/contacts.py
PqrUploadModule/contacts_update.py
PqrUploadModule/hard_coded_relations.py
PqrUploadModule/incidents.py
PqrUploadModule/notes.py
PqrUploadModule/scanning.py
PqrUploadModule/start_settings.py
PqrUploadModule/ticket_incidents_counterparts.py
PqrUploadModule/tickets.py
PqrUploadModule/tickets_incidents_counterparts.py