Metadata-Version: 2.1
Name: PqrUpload4-pkg-petronije
Version: 0.0.4
Summary: A small example package
Home-page: https://github.com/petronije2002/PqrUpload/
Author: Example Author
Author-email: petronije2002@gmail.com
License: UNKNOWN
Platform: UNKNOWN
Classifier: Programming Language :: Python :: 3
Classifier: License :: OSI Approved :: MIT License
Classifier: Operating System :: OS Independent
Requires-Python: ==3.6
